bong/__init__.py
bong/cli.py
bong/metadata.py
bong/notify.py
bong/parse_args.py
bong/run.py
bong/settings.py
bong-1.1.4.dist-info/zip-safe
bong-1.1.4.dist-info/top_level.txt
bong-1.1.4.dist-info/entry_points.txt
bong-1.1.4.dist-info/METADATA
bong-1.1.4.dist-info/DESCRIPTION.rst
bong-1.1.4.dist-info/metadata.json
bong-1.1.4.dist-info/WHEEL
bong-1.1.4.dist-info/RECORD
