Metadata-Version: 2.0
Name: bong
Version: 1.1.4
Summary: Wait for a period of time, then display a notification.
Home-page: https://github.com/prophile/bong
Author: Alistair Lynn
Author-email: arplynn@gmail.com
License: MIT
Platform: UNKNOWN
Classifier: Development Status :: 5 - Production/Stable
Classifier: Environment :: X11 Applications :: Gnome
Classifier: Environment :: MacOS X
Classifier: License :: OSI Approved :: MIT License
Classifier: Operating System :: POSIX
Classifier: Programming Language :: Python :: 3.4
Classifier: Topic :: Office/Business
